Metadata-Version: 1.0
Name: awordaday
Version: 0.1.0
Summary: Adding fun to boring http headers
Home-page: UNKNOWN
Author: Jacques-Olivier D. Bernier
Author-email: me@jackdbernier.com
License: MIT
Platform: UNKNOWN
